{
	"name"      : "CreateCamera",
	"pos"       : [150, 100],
	"varname"   : "instCamera",
	"funcname"  : "create",
	"customfunc" : "function CreateCamera() return { camera=function(self) return self.m_cam end, create=function(self) self.m_cam = Camera(); self.m_cam:SetScreenSize(1024, 1024); self.m_cam:SetFilename('render_obj.jpg'); self.m_cam:LookAt(0, 0, -300, 0, 0, 0, 0, 1, 0, 60) end} end\n",
	"deletable": false,
	"cameradata" : [
		0,0,-300,
		0,0,0,
		0,1,0,
		60,
	],
	"input": [
	],
	"output": [
		{"name": "Camera", "type": "Camera"}
	]
}
